BacterialTyper/__init__.py
BacterialTyper/config/__init__.py
BacterialTyper/config/extern_progs.py
BacterialTyper/config/install_dependencies.py
BacterialTyper/config/set_config.py
BacterialTyper/config/R/R_dependencies.csv
BacterialTyper/config/R/R_package.info.txt
BacterialTyper/config/R/check_install_path.R
BacterialTyper/config/R/check_install_system.R
BacterialTyper/config/R/install_github.R
BacterialTyper/config/R/install_package.R
BacterialTyper/config/perl/IslandPath_dependencies.csv
BacterialTyper/config/perl/install_perl_packages.py
BacterialTyper/config/perl/perl_dependencies.csv
BacterialTyper/config/python/name_conversion_module.csv
BacterialTyper/config/python/python_requirements.txt
BacterialTyper/config/python/python_requirements_summary.csv
BacterialTyper/config/software/dependencies.csv
BacterialTyper/config/software/software_details.csv
BacterialTyper/data/BUSCO_dataset.csv
BacterialTyper/data/PubMLST_datasets.csv
BacterialTyper/data/__init__.py
BacterialTyper/data/__init__.pyc
BacterialTyper/data/available_Trimmomatic_adapters.fasta
BacterialTyper/data/available_Trimmomatic_adapters_info.csv
BacterialTyper/data/available_plasmids_data.txt
BacterialTyper/data/data_files.py
BacterialTyper/data/data_files.pyc
BacterialTyper/data/toDownload.csv
BacterialTyper/modules/MGE.py
BacterialTyper/modules/__init__.py
BacterialTyper/modules/annot.py
BacterialTyper/modules/assemble.py
BacterialTyper/modules/citation.py
BacterialTyper/modules/cluster.py
BacterialTyper/modules/config.py
BacterialTyper/modules/database.py
BacterialTyper/modules/help_info.py
BacterialTyper/modules/ident.py
BacterialTyper/modules/metadata.py
BacterialTyper/modules/phylo.py
BacterialTyper/modules/prep.py
BacterialTyper/modules/profile.py
BacterialTyper/modules/qc.py
BacterialTyper/modules/report_generation.py
BacterialTyper/modules/run.py
BacterialTyper/modules/test.py
BacterialTyper/modules/trim.py
BacterialTyper/modules/version.py
BacterialTyper/other_tools/__init__.py
BacterialTyper-0.6.7.dist-info/LICENSE
BacterialTyper-0.6.7.dist-info/METADATA
BacterialTyper-0.6.7.dist-info/WHEEL
BacterialTyper-0.6.7.dist-info/top_level.txt
BacterialTyper-0.6.7.dist-info/RECORD
