Metadata-Version: 2.1
Name: BacterialTyper
Version: 0.6.7
Summary: UNKNOWN
Home-page: https://github.com/HCGB-IGTP/BacterialTyper/
Author: Jose F. Sanchez-Herrero
Author-email: jfbioinformatics@gmail.com
License: MIT License
Platform: UNKNOWN
Classifier: Programming Language :: Python :: 3
Classifier: License :: OSI Approved :: MIT License
Classifier: Operating System :: OS Independent
Requires-Dist: ariba
Requires-Dist: assembly-stats
Requires-Dist: bcbio-gff
Requires-Dist: beautifulsoup4
Requires-Dist: biopython
Requires-Dist: card-trick
Requires-Dist: ete3
Requires-Dist: future
Requires-Dist: HCGB
Requires-Dist: multiqc
Requires-Dist: ncbi-genome-download
Requires-Dist: networkx
Requires-Dist: numpy
Requires-Dist: pandas
Requires-Dist: patool
Requires-Dist: PhiSpy
Requires-Dist: scipy
Requires-Dist: sourmash
Requires-Dist: spaTyper
Requires-Dist: wget
Requires-Dist: XlsxWriter
Requires-Dist: pytest
